sciline/__init__.py
sciline/_provider.py
sciline/_utils.py
sciline/data_graph.py
sciline/display.py
sciline/domain.py
sciline/handler.py
sciline/pipeline.py
sciline/py.typed
sciline/reporter.py
sciline/scheduler.py
sciline/task_graph.py
sciline/typing.py
sciline/visualize.py
sciline/serialize/__init__.py
sciline/serialize/_json.py
sciline/serialize/graph_json_schema.json
sciline/sphinxext/__init__.py
sciline/sphinxext/domain_types.py
sciline-25.11.1.dist-info/licenses/LICENSE
sciline-25.11.1.dist-info/METADATA
sciline-25.11.1.dist-info/WHEEL
sciline-25.11.1.dist-info/top_level.txt
sciline-25.11.1.dist-info/RECORD
